isd/__init__.py
isd/batch.py
isd/cli.py
isd/errors.py
isd/io.py
isd/py.typed
isd/record.py
isd-0.3.0.dist-info/LICENSE
isd-0.3.0.dist-info/METADATA
isd-0.3.0.dist-info/WHEEL
isd-0.3.0.dist-info/entry_points.txt
isd-0.3.0.dist-info/top_level.txt
isd-0.3.0.dist-info/RECORD
