Metadata-Version: 2.1
Name: isd
Version: 0.3.0
Summary: Reads and archives NOAA Integrated Surface Database (ISD) files
Author-email: Pete Gadomski <pete.gadomski@gmail.com>
License: Apache-2.0
Classifier: Programming Language :: Python :: 3
Classifier: License :: OSI Approved :: Apache Software License
Classifier: Operating System :: OS Independent
Requires-Python: >=3.9
License-File: LICENSE
Requires-Dist: click ~=8.0
Requires-Dist: pandas ~=1.3
Provides-Extra: dev
Requires-Dist: mypy ~=1.2 ; extra == 'dev'
Requires-Dist: pre-commit ~=3.2 ; extra == 'dev'
Requires-Dist: pytest ~=8.0 ; extra == 'dev'
Requires-Dist: ruff ~=0.1.9 ; extra == 'dev'
Provides-Extra: docs
Requires-Dist: sphinx ~=7.2 ; extra == 'docs'
Provides-Extra: examples
Requires-Dist: tqdm ~=4.66 ; extra == 'examples'
